alembic.ini
compose.neo4j.yaml
compose.ollama.yaml
compose.postgres.yaml
compose.yaml
kense_r2r/__init__.py
kense_r2r/agent/__init__.py
kense_r2r/agent/base.py
kense_r2r/agent/rag.py
kense_r2r/base/__init__.py
kense_r2r/base/abstractions/__init__.py
kense_r2r/base/abstractions/base.py
kense_r2r/base/abstractions/completion.py
kense_r2r/base/abstractions/document.py
kense_r2r/base/abstractions/embedding.py
kense_r2r/base/abstractions/exception.py
kense_r2r/base/abstractions/graph.py
kense_r2r/base/abstractions/llm.py
kense_r2r/base/abstractions/prompt.py
kense_r2r/base/abstractions/search.py
kense_r2r/base/abstractions/user.py
kense_r2r/base/abstractions/vector.py
kense_r2r/base/agent/__init__.py
kense_r2r/base/agent/agent.py
kense_r2r/base/agent/base.py
kense_r2r/base/api/models/__init__.py
kense_r2r/base/api/models/auth/__init__.py
kense_r2r/base/api/models/auth/responses.py
kense_r2r/base/api/models/base.py
kense_r2r/base/api/models/ingestion/__init__.py
kense_r2r/base/api/models/ingestion/responses.py
kense_r2r/base/api/models/management/__init__.py
kense_r2r/base/api/models/management/responses.py
kense_r2r/base/api/models/retrieval/__init__.py
kense_r2r/base/api/models/retrieval/responses.py
kense_r2r/base/logging/__init__.py
kense_r2r/base/logging/base.py
kense_r2r/base/logging/log_processor.py
kense_r2r/base/logging/run_logger.py
kense_r2r/base/logging/run_manager.py
kense_r2r/base/parsers/__init__.py
kense_r2r/base/parsers/base_parser.py
kense_r2r/base/pipeline/__init__.py
kense_r2r/base/pipeline/base_pipeline.py
kense_r2r/base/pipes/__init__.py
kense_r2r/base/pipes/base_pipe.py
kense_r2r/base/providers/__init__.py
kense_r2r/base/providers/auth.py
kense_r2r/base/providers/base.py
kense_r2r/base/providers/chunking.py
kense_r2r/base/providers/crypto.py
kense_r2r/base/providers/database.py
kense_r2r/base/providers/embedding.py
kense_r2r/base/providers/kg.py
kense_r2r/base/providers/llm.py
kense_r2r/base/providers/parsing.py
kense_r2r/base/providers/prompt.py
kense_r2r-0.2.85.dist-info/LICENSE.md
kense_r2r-0.2.85.dist-info/METADATA
kense_r2r-0.2.85.dist-info/WHEEL
kense_r2r-0.2.85.dist-info/entry_points.txt
kense_r2r-0.2.85.dist-info/RECORD
