Metadata-Version: 2.1
Name: kense_r2r
Version: 0.2.85
Summary: SciPhi R2R
License: MIT
Author: Owen Colegrove
Author-email: owen@sciphi.ai
Requires-Python: >=3.9,<3.13
Classifier: License :: OSI Approved :: MIT License
Classifier: Programming Language :: Python :: 3
Classifier: Programming Language :: Python :: 3.9
Classifier: Programming Language :: Python :: 3.10
Classifier: Programming Language :: Python :: 3.11
Classifier: Programming Language :: Python :: 3.12
Provides-Extra: all
Provides-Extra: ingest-movies
Requires-Dist: aiosqlite (>=0.20.0,<0.21.0)
Requires-Dist: alembic (>=1.13.2,<2.0.0)
Requires-Dist: asyncpg (>=0.29.0,<0.30.0)
Requires-Dist: bcrypt (>=4.1.3,<5.0.0)
Requires-Dist: beautifulsoup4 (>=4.12.3,<5.0.0)
Requires-Dist: deepdiff (>=7.0.1,<8.0.0)
Requires-Dist: fastapi (>=0.109.2,<0.110.0)
Requires-Dist: fire (>=0.5.0,<0.6.0)
Requires-Dist: fsspec (>=2024.6.0,<2025.0.0)
Requires-Dist: graspologic (>=3.4.1,<4.0.0)
Requires-Dist: gunicorn (>=21.2.0,<22.0.0)
Requires-Dist: litellm (>=1.42.3,<2.0.0)
Requires-Dist: markdown (>=3.6,<4.0)
Requires-Dist: moviepy (>=1.0.3,<2.0.0) ; extra == "all" or extra == "ingest-movies"
Requires-Dist: neo4j (>=5.21.0,<6.0.0)
Requires-Dist: nest-asyncio (>=1.6.0,<2.0.0)
Requires-Dist: ollama (>=0.2.1,<0.3.0)
Requires-Dist: openai (>=1.11.1,<2.0.0)
Requires-Dist: opencv-python (>=4.10.0.82,<5.0.0.0) ; extra == "all" or extra == "ingest-movies"
Requires-Dist: openpyxl (>=3.1.2,<4.0.0)
Requires-Dist: passlib (>=1.7.4,<2.0.0)
Requires-Dist: poppler-utils (>=0.1.0,<0.2.0)
Requires-Dist: posthog (>=3.5.0,<4.0.0)
Requires-Dist: psutil (>=6.0.0,<7.0.0)
Requires-Dist: pydantic[email] (>=2.8.2,<3.0.0)
Requires-Dist: pyjwt (>=2.8.0,<3.0.0)
Requires-Dist: pypdf (>=4.2.0,<5.0.0)
Requires-Dist: python-docx (>=1.1.0,<2.0.0)
Requires-Dist: python-multipart (>=0.0.9,<0.0.10)
Requires-Dist: python-pptx (>=0.6.23,<0.7.0)
Requires-Dist: pyyaml (>=6.0.1,<7.0.0)
Requires-Dist: redis (>=5.0.4,<6.0.0)
Requires-Dist: requests (>=2.31.0,<3.0.0)
Requires-Dist: sqlalchemy (>=2.0.30,<3.0.0)
Requires-Dist: toml (>=0.10.2,<0.11.0)
Requires-Dist: types-requests (>=2.31.0,<3.0.0)
Requires-Dist: uvicorn (>=0.27.0.post1,<0.28.0)
Requires-Dist: vecs (>=0.4.0,<0.5.0)
